musing/__init__.py
musing/common_util.py
musing/musing.py
musing/musthe.py
musing-1.0.2.dist-info/DESCRIPTION.rst
musing-1.0.2.dist-info/METADATA
musing-1.0.2.dist-info/RECORD
musing-1.0.2.dist-info/WHEEL
musing-1.0.2.dist-info/metadata.json
musing-1.0.2.dist-info/top_level.txt
