Metadata-Version: 2.0
Name: musing
Version: 1.0.2
Summary: A Music theme lib for human
Home-page: https://github.com/lfzark/musing
Author: ark1ee
Author-email: onlyarter@gmail.com
License: UNKNOWN
Keywords: music  melody lib
Platform: UNKNOWN
Classifier: Development Status :: 3 - Alpha
Classifier: Intended Audience :: Developers
Classifier: Topic :: Software Development :: Build Tools
Classifier: License :: OSI Approved :: MIT License
Classifier: Programming Language :: Python :: 2
Classifier: Programming Language :: Python :: 2.7
Provides-Extra: dev
Provides-Extra: test
Requires-Dist: pretty-midi
Provides-Extra: dev
Requires-Dist: check-manifest; extra == 'dev'
Provides-Extra: test
Requires-Dist: coverage; extra == 'test'
